Metadata-Version: 2.1
Name: xesg
Version: 1.0.4
Summary: 学而思编程全工作室官方库
Home-page: https://github.com/
Author: Jianrui Li
Author-email: lijianrui7560@qq.com
License: UNKNOWN
Platform: UNKNOWN
Classifier: Programming Language :: Python :: 3
Classifier: License :: OSI Approved :: MIT License
Classifier: Operating System :: OS Independent
